hcdk_eks/__init__.py
hcdk_eks/eks_cluster.py
tests/__init__.py
tests/sample_stack.py
tests/sample_stack_with_vpc.py
tests/unit/__init__.py
tests/unit/test_eks_cluster.py
tests/unit/test_eks_cluster_with_vpc.py
hcdk_eks-0.0.3.dist-info/LICENSE
hcdk_eks-0.0.3.dist-info/METADATA
hcdk_eks-0.0.3.dist-info/WHEEL
hcdk_eks-0.0.3.dist-info/top_level.txt
hcdk_eks-0.0.3.dist-info/RECORD
