Metadata-Version: 2.1
Name: hcdk-eks
Version: 0.0.3
Summary: EKS library for the Halloumi modules of the AWS CDK
Home-page: UNKNOWN
License: UNKNOWN
Platform: UNKNOWN
Requires-Dist: aws-cdk.aws-autoscaling
Requires-Dist: aws-cdk.aws-ec2
Requires-Dist: aws-cdk.aws-eks
Requires-Dist: aws-cdk.aws-iam
Requires-Dist: aws-cdk.core
